currency_mcp/__init__.py
currency_mcp/server.py
currency_history_mcp-0.1.0.dist-info/METADATA
currency_history_mcp-0.1.0.dist-info/WHEEL
currency_history_mcp-0.1.0.dist-info/entry_points.txt
currency_history_mcp-0.1.0.dist-info/RECORD
