Metadata-Version: 2.4
Name: currency-history-mcp
Version: 0.1.0
Summary: A Model Context Protocol (MCP) server for fetching historical currency exchange rates using the Frankfurter API.
Project-URL: Homepage, https://github.com/example/currency_mcp
Author-email: User <user@example.com>
License-Expression: MIT
Keywords: currency,exchange-rates,frankfurter,history,mcp
Requires-Python: >=3.10
Requires-Dist: fastmcp
Requires-Dist: httpx
